ttrs_quicfire/__init__.py
ttrs_quicfire/build_FF_domain.py
ttrs_quicfire/build_shapefiles.py
ttrs_quicfire/dat_file_functions.py
ttrs_quicfire/exceptions.py
ttrs_quicfire/print_inp_files.py
ttrs_quicfire/quic_fire.py
ttrs_quicfire-1.1.1.dist-info/LICENSE.md
ttrs_quicfire-1.1.1.dist-info/METADATA
ttrs_quicfire-1.1.1.dist-info/WHEEL
ttrs_quicfire-1.1.1.dist-info/top_level.txt
ttrs_quicfire-1.1.1.dist-info/RECORD
