Metadata-Version: 2.1
Name: ttrs-quicfire
Version: 1.1.1
Summary: ttrs_quicfire is a Python library to easily configure burn models for plots of land defined using shape files for the quicfire model.
Home-page: https://github.com/QUIC-Fire-TT/ttrs_quicfire
Author: Zachary Cope
Author-email: zcope@talltimbers.org
License: MIT
Project-URL: Source, https://github.com/QUIC-Fire-TT/ttrs_quicfire
Project-URL: Tracker, https://github.com/QUIC-Fire-TT/ttrs_quicfireissues
Platform: UNKNOWN
Classifier: Intended Audience :: Developers
Classifier: Topic :: Scientific/Engineering :: GIS
Classifier: Topic :: Scientific/Engineering :: Visualization
Classifier: License :: OSI Approved :: MIT License
License-File: LICENSE.md
Requires-Dist: numpy
Requires-Dist: scipy
Requires-Dist: geopandas
Requires-Dist: pandas
Requires-Dist: gdal
Requires-Dist: rasterio
Requires-Dist: fastfuels
Requires-Dist: shapely
